nijtaio/__init__.py
nijtaio/_version.py
nijtaio/cli.py
nijtaio-1.1.13.dist-info/METADATA
nijtaio-1.1.13.dist-info/WHEEL
nijtaio-1.1.13.dist-info/entry_points.txt
nijtaio-1.1.13.dist-info/top_level.txt
nijtaio-1.1.13.dist-info/RECORD
