Metadata-Version: 2.1
Name: nijtaio
Version: 1.1.13
Summary: Helper module to streamline access to Nijta's API
Project-URL: Documentation, https://docs.nijta.com
Project-URL: Bug Tracker, https://github.com/Nijta/nijta-samples/issues
Classifier: Intended Audience :: Developers
Classifier: License :: Other/Proprietary License
Requires-Dist: requests
Requires-Dist: soundfile
Requires-Dist: librosa
Requires-Dist: datasets
Requires-Dist: fire
